latinwordnet/__init__.py
latinwordnet/latinwordnet.py
tests/__init__.py
tests/test_index.py
tests/test_latinwordnet.py
tests/test_lemmas.py
tests/test_other.py
tests/test_semfields.py
tests/test_sentiment_analysis.py
tests/test_synsets.py
latinwordnet-0.3.1.dist-info/METADATA
latinwordnet-0.3.1.dist-info/WHEEL
latinwordnet-0.3.1.dist-info/top_level.txt
latinwordnet-0.3.1.dist-info/RECORD
