Metadata-Version: 2.1
Name: latinwordnet
Version: 0.3.1
Summary: A light-weight Python wrapper for the Latin WordNet API
Home-page: https://github.com/wmshort/latinwordnet
Author: William Michael Short
Author-email: w.short@exeter.ac.uk
License: GNU General Public License v3.0
Platform: UNKNOWN
Requires-Dist: requests (>=2.22.0)
Requires-Dist: python-dotenv (>=0.12.0)
